Metadata-Version: 1.0
Name: CEF4pygame
Version: 0.0
Summary: Can display web pages using pygame
Home-page: UNKNOWN
Author: UNKNOWN
Author-email: yegor.l.2025@gmail.com
License: UNKNOWN
Platform: UNKNOWN
